qpsolversbench/diagnostics/__init__.py
qpsolversbench/diagnostics/explain.py
qpsolversbench/diagnostics/largest_discrepancy.py
qpsolversbench/diagnostics/performance.py
qpsolversbench/problems/__init__.py
qpsolversbench/problems/caron_problems.py
qpsolversbench/problems/financial_problems.py
qpsolversbench/problems/solved_problems.py
qpsolversbench-0.0.3.dist-info/LICENSE
qpsolversbench-0.0.3.dist-info/METADATA
qpsolversbench-0.0.3.dist-info/WHEEL
qpsolversbench-0.0.3.dist-info/entry_points.txt
qpsolversbench-0.0.3.dist-info/top_level.txt
qpsolversbench-0.0.3.dist-info/RECORD
