Metadata-Version: 2.1
Name: qpsolversbench
Version: 0.0.3
Summary: Evaluation of quadratic solvers using qpsolvers
Home-page: https://github.com/microprediction/qpsolversbench
Author: microprediction
Author-email: peter.cotton@microprediction.com
License: MIT
Classifier: License :: OSI Approved :: MIT License
Classifier: Programming Language :: Python :: 3
Classifier: Programming Language :: Python :: 3.7
Classifier: Programming Language :: Python :: 3.8
Classifier: Programming Language :: Python :: 3.9
License-File: LICENSE
Requires-Dist: wheel
Requires-Dist: precise
Requires-Dist: qpsolvers (>=2.7.3)
